LICENCE.txt
MANIFEST.in
README.rst
setup.py
emencia_django_slideshows.egg-info/PKG-INFO
emencia_django_slideshows.egg-info/SOURCES.txt
emencia_django_slideshows.egg-info/dependency_links.txt
emencia_django_slideshows.egg-info/not-zip-safe
emencia_django_slideshows.egg-info/requires.txt
emencia_django_slideshows.egg-info/top_level.txt
slideshows/__init__.py
slideshows/admin.py
slideshows/models.py
slideshows/settings.py
slideshows/urls.py
slideshows/utils.py
slideshows/views.py
slideshows/migrations/0001_initial.py
slideshows/migrations/__init__.py
slideshows/templates/slideshows/random_slide/default.html
slideshows/templates/slideshows/slides_show/default.html
slideshows/templates/slideshows/slides_show/configs/default.html
slideshows/templatetags/__init__.py
slideshows/templatetags/slideshows_tags.py