Metadata-Version: 1.1
Name: emencia-django-slideshows
Version: 1.0.1
Summary: 
